reprit/__init__.py
reprit/base.py
reprit/hints.py
reprit/py.typed
reprit/seekers.py
reprit/serializers.py
reprit/serializers.pyi
reprit/core/__init__.py
reprit/core/hints.py
reprit/core/utils.py
reprit-0.9.0.dist-info/LICENSE
reprit-0.9.0.dist-info/METADATA
reprit-0.9.0.dist-info/WHEEL
reprit-0.9.0.dist-info/top_level.txt
reprit-0.9.0.dist-info/RECORD
