Metadata-Version: 2.1
Name: reprit
Version: 0.9.0
Home-page: https://github.com/lycantropos/reprit/
Download-URL: https://github.com/lycantropos/reprit/archive/master.zip
Author-email: Azat Ibrakov <azatibrakov@gmail.com>
License: MIT License
Classifier: License :: OSI Approved :: MIT License
Classifier: Programming Language :: Python :: 3.7
Classifier: Programming Language :: Python :: 3.8
Classifier: Programming Language :: Python :: 3.9
Classifier: Programming Language :: Python :: 3.10
Classifier: Programming Language :: Python :: 3.11
Classifier: Programming Language :: Python :: Implementation :: CPython
Classifier: Programming Language :: Python :: Implementation :: PyPy
Classifier: Programming Language :: Python :: Implementation :: CPython
Classifier: Programming Language :: Python :: Implementation :: PyPy
Requires-Python: >=3.7
Provides-Extra: tests
License-File: LICENSE
